repliconfig/__init__.py
repliconfig/config.py
repliconfig/configurable.py
repliconfig/statistics.py
repliconfig-0.0.1.dist-info/LICENSE
repliconfig-0.0.1.dist-info/METADATA
repliconfig-0.0.1.dist-info/WHEEL
repliconfig-0.0.1.dist-info/top_level.txt
repliconfig-0.0.1.dist-info/RECORD
