Metadata-Version: 2.1
Name: repliconfig
Version: 0.0.1
Summary: Replicable Configurations for Scientific Projects
Home-page: https://github.com/mbodensohn/repliconfig
Author: Jan-Micha Bodensohn
Classifier: Programming Language :: Python :: 3
Classifier: License :: OSI Approved :: MIT License
Classifier: Operating System :: OS Independent
Requires-Python: >=3.6
License-File: LICENSE
